logger_telegram_v/__init__.py
logger_telegram_v/logger.py
logger_telegram_v/logger_handler.py
logger_telegram_v/telegram_logger.py
logger_telegram_v-0.1.0.dist-info/METADATA
logger_telegram_v-0.1.0.dist-info/WHEEL
logger_telegram_v-0.1.0.dist-info/top_level.txt
logger_telegram_v-0.1.0.dist-info/RECORD
