Metadata-Version: 2.1
Name: logger-telegram-v
Version: 0.1.0
Summary: A library for sending logs to Telegram
Home-page: https://github.com/yourusername/logger-telegram-v
Author: Vatche Thorossian
Author-email: vatche.thorossian@gmail.com
License: UNKNOWN
Platform: UNKNOWN
Classifier: Development Status :: 3 - Alpha
Classifier: Intended Audience :: Developers
Classifier: License :: OSI Approved :: MIT License
Classifier: Programming Language :: Python :: 3
Classifier: Programming Language :: Python :: 3.6
Classifier: Programming Language :: Python :: 3.7
Classifier: Programming Language :: Python :: 3.8
Classifier: Programming Language :: Python :: 3.9
Classifier: Programming Language :: Python :: 3.10
Classifier: Programming Language :: Python :: 3.11
Requires-Dist: loguru
Requires-Dist: python-telegram-bot
